odoo10_addon_account_move_base_import-10.0.1.1.1-py3.8-nspkg.pth
odoo/addons/account_move_base_import/README.rst
odoo/addons/account_move_base_import/__init__.py
odoo/addons/account_move_base_import/__manifest__.py
odoo/addons/account_move_base_import/data/completion_rule_data.xml
odoo/addons/account_move_base_import/data/statement.csv
odoo/addons/account_move_base_import/data/statement.xls
odoo/addons/account_move_base_import/i18n/account_move_base_import.pot
odoo/addons/account_move_base_import/i18n/am.po
odoo/addons/account_move_base_import/i18n/ar.po
odoo/addons/account_move_base_import/i18n/bg.po
odoo/addons/account_move_base_import/i18n/bs.po
odoo/addons/account_move_base_import/i18n/ca.po
odoo/addons/account_move_base_import/i18n/cs.po
odoo/addons/account_move_base_import/i18n/da.po
odoo/addons/account_move_base_import/i18n/de.po
odoo/addons/account_move_base_import/i18n/el_GR.po
odoo/addons/account_move_base_import/i18n/en_GB.po
odoo/addons/account_move_base_import/i18n/es.po
odoo/addons/account_move_base_import/i18n/es_AR.po
odoo/addons/account_move_base_import/i18n/es_CL.po
odoo/addons/account_move_base_import/i18n/es_CO.po
odoo/addons/account_move_base_import/i18n/es_CR.po
odoo/addons/account_move_base_import/i18n/es_DO.po
odoo/addons/account_move_base_import/i18n/es_EC.po
odoo/addons/account_move_base_import/i18n/es_ES.po
odoo/addons/account_move_base_import/i18n/es_MX.po
odoo/addons/account_move_base_import/i18n/es_PE.po
odoo/addons/account_move_base_import/i18n/es_PY.po
odoo/addons/account_move_base_import/i18n/es_VE.po
odoo/addons/account_move_base_import/i18n/et.po
odoo/addons/account_move_base_import/i18n/eu.po
odoo/addons/account_move_base_import/i18n/fa.po
odoo/addons/account_move_base_import/i18n/fi.po
odoo/addons/account_move_base_import/i18n/fr.po
odoo/addons/account_move_base_import/i18n/fr_CA.po
odoo/addons/account_move_base_import/i18n/fr_CH.po
odoo/addons/account_move_base_import/i18n/gl.po
odoo10_addon_account_move_base_import-10.0.1.1.1.dist-info/METADATA
odoo10_addon_account_move_base_import-10.0.1.1.1.dist-info/WHEEL
odoo10_addon_account_move_base_import-10.0.1.1.1.dist-info/namespace_packages.txt
odoo10_addon_account_move_base_import-10.0.1.1.1.dist-info/top_level.txt
odoo10_addon_account_move_base_import-10.0.1.1.1.dist-info/RECORD
